onefiler/__init__.py
onefiler/main.py
onefiler-0.0.1.dist-info/LICENSE
onefiler-0.0.1.dist-info/METADATA
onefiler-0.0.1.dist-info/WHEEL
onefiler-0.0.1.dist-info/entry_points.txt
onefiler-0.0.1.dist-info/top_level.txt
onefiler-0.0.1.dist-info/RECORD
