Metadata-Version: 2.1
Name: onefiler
Version: 0.0.1
Summary: A tool to create a unique file with contents of other files
Home-page: https://github.com/fabiopipitone/onefiler
Author: Fabio Pipitone
Author-email: fabio.pipitone93@gmail.com
Classifier: Programming Language :: Python :: 3
Classifier: Operating System :: OS Independent
License-File: LICENSE
